librep/__init__.py
librep-0.0.5.data/scripts/librep
librep-0.0.5.dist-info/LICENSE
librep-0.0.5.dist-info/METADATA
librep-0.0.5.dist-info/WHEEL
librep-0.0.5.dist-info/top_level.txt
librep-0.0.5.dist-info/RECORD
