Metadata-Version: 2.1
Name: librep
Version: 0.0.5
Summary: Python-based command line tool to replace text/code in files
Home-page: https://github.com/umami-hep/librep
Keywords: tools
Requires-Python: >=3.8
License-File: LICENSE
